pinjected_anthropic/__init__.py
pinjected_anthropic/llm.py
pinjected_anthropic-0.1.18.dist-info/METADATA
pinjected_anthropic-0.1.18.dist-info/WHEEL
pinjected_anthropic-0.1.18.dist-info/RECORD
