Metadata-Version: 2.3
Name: pinjected-anthropic
Version: 0.1.18
Summary: Add your description here
Author-email: proboscis <nameissoap@gmail.com>
Requires-Python: >=3.8
Requires-Dist: anthropic>=0.39.0
Requires-Dist: pandas>=2.2.2
Requires-Dist: pillow>=10.4.0
Requires-Dist: pinjected>=0.2.189
Requires-Dist: pydantic>=2.9.2
